prtgitlog/__init__.py
prtgitlog/cli.py
prtgitlog/commit_aliases.py
prtgitlog/commit_files.py
prtgitlog/commit_info.py
prtgitlog/gitlog.py
prtgitlog/gitlog_strm.py
prtgitlog/main.py
prtgitlog/prtlog.py
prtgitlog/sortbytime.py
prtgitlog-0.1.21.dist-info/licenses/LICENSE
prtgitlog-0.1.21.dist-info/METADATA
prtgitlog-0.1.21.dist-info/WHEEL
prtgitlog-0.1.21.dist-info/entry_points.txt
prtgitlog-0.1.21.dist-info/top_level.txt
prtgitlog-0.1.21.dist-info/RECORD
