Metadata-Version: 2.4
Name: prtgitlog
Version: 0.1.21
Summary: A script to print 'git log' output in a concise informative format
Author-email: "DV Klopfenstein, PhD" <dvklopfenstein@protonmail.com>
License-Expression: AGPL-3.0-or-later
Project-URL: Homepage, https://github.com/dvklopfenstein/prtgitlog
Classifier: Programming Language :: Python
Classifier: Environment :: Console
Classifier: Intended Audience :: Developers
Classifier: Development Status :: 3 - Alpha
Classifier: Programming Language :: Python
Classifier: Programming Language :: Python :: 2
Classifier: Programming Language :: Python :: 3
Classifier: Topic :: Software Development :: Version Control :: Git
License-File: LICENSE
Requires-Dist: docopt
Dynamic: license-file
